mcp_server_composer/__init__.py
mcp_server_composer/__main__.py
mcp_server_composer/__version__.py
mcp_server_composer/cli.py
mcp_server_composer/composer.py
mcp_server_composer/discovery.py
mcp_server_composer/exceptions.py
mcp_server_composer-0.1.0.dist-info/METADATA
mcp_server_composer-0.1.0.dist-info/WHEEL
mcp_server_composer-0.1.0.dist-info/entry_points.txt
mcp_server_composer-0.1.0.dist-info/licenses/LICENSE
mcp_server_composer-0.1.0.dist-info/RECORD
