Metadata-Version: 2.4
Name: mcp_server_composer
Version: 0.1.0
Project-URL: Home, https://github.com/datalayer/mcp-server-composer
Project-URL: Documentation, https://github.com/datalayer/mcp-server-composer
Project-URL: Repository, https://github.com/datalayer/mcp-server-composer
Project-URL: Issues, https://github.com/datalayer/mcp-server-composer/issues
Author-email: Datalayer <info@datalayer.io>
License: BSD 3-Clause License
License-File: LICENSE
Keywords: Composition,MCP,Model Context Protocol,Server
Classifier: Intended Audience :: Developers
Classifier: Intended Audience :: System Administrators
Classifier: License :: OSI Approved :: BSD License
Classifier: Programming Language :: Python
Classifier: Programming Language :: Python :: 3
Classifier: Programming Language :: Python :: 3.10
Classifier: Programming Language :: Python :: 3.11
Classifier: Programming Language :: Python :: 3.12
Requires-Python: >=3.10
Requires-Dist: importlib-metadata>=4.8.0
Requires-Dist: mcp[cli]>=1.2.1
Requires-Dist: toml>=0.10.2
Requires-Dist: typing-extensions>=4.0.0
Provides-Extra: dev
Requires-Dist: pre-commit>=3.0.0; extra == 'dev'
Provides-Extra: lint
Requires-Dist: mypy>=1.0.0; extra == 'lint'
Requires-Dist: ruff>=0.1.0; extra == 'lint'
Provides-Extra: test
Requires-Dist: pytest-asyncio>=0.21.0; extra == 'test'
Requires-Dist: pytest-cov>=4.0.0; extra == 'test'
Requires-Dist: pytest>=7.0; extra == 'test'
